aionowplaying/__init__.py
aionowplaying/interface/__init__.py
aionowplaying/interface/base.py
aionowplaying/interface/macos.py
aionowplaying/interface/mpris2.py
aionowplaying/interface/windows.py
aionowplaying-0.10.1.dist-info/METADATA
aionowplaying-0.10.1.dist-info/WHEEL
aionowplaying-0.10.1.dist-info/licenses/LICENSE.txt
aionowplaying-0.10.1.dist-info/RECORD
