Metadata-Version: 2.4
Name: aionowplaying
Version: 0.10.1
Summary: A cross-platform Now Playing client
License: GPL-3.0-only
License-File: LICENSE.txt
Keywords: nowplaying,mpris
Author: Bruce Zhang
Author-email: zttt183525594@gmail.com
Maintainer: Bruce Zhang
Maintainer-email: zttt183525594@gmail.com
Requires-Python: >=3.7
Classifier: License :: OSI Approved :: GNU General Public License v3 (GPLv3)
Classifier: Programming Language :: Python :: 3
Classifier: Programming Language :: Python :: 3.7
Classifier: Programming Language :: Python :: 3.8
Classifier: Programming Language :: Python :: 3.9
Classifier: Programming Language :: Python :: 3.10
Classifier: Programming Language :: Python :: 3.11
Classifier: Programming Language :: Python :: 3.12
Classifier: Programming Language :: Python :: 3.13
Classifier: Programming Language :: Python :: 3.14
Requires-Dist: dbus-next ; sys_platform == "linux"
Requires-Dist: pydantic
Requires-Dist: pyobjc-framework-Cocoa ; sys_platform == "darwin"
Requires-Dist: pyobjc-framework-MediaPlayer ; sys_platform == "darwin"
Requires-Dist: winsdk ; sys_platform == "win32"
Project-URL: Bug Tracker, https://github.com/BruceZhang1993/aionowplaying/issues
Project-URL: Repository, https://github.com/BruceZhang1993/aionowplaying
